donutLol/__init__.py
donutLol/donutLol.py
donutLol-0.0.9.data/scripts/donut.bat
donutLol-0.0.9.data/scripts/donut.py
donutLol-0.0.9.dist-info/LICENSE
donutLol-0.0.9.dist-info/METADATA
donutLol-0.0.9.dist-info/WHEEL
donutLol-0.0.9.dist-info/top_level.txt
donutLol-0.0.9.dist-info/RECORD
